nonebot_plugin_auto_teenstudy/__init__.py
nonebot_plugin_auto_teenstudy/data/dxx_answer.json
nonebot_plugin_auto_teenstudy/data/dxx_help.txt
nonebot_plugin_auto_teenstudy/data/dxx_jx.json
nonebot_plugin_auto_teenstudy/data/dxx_list.json
nonebot_plugin_auto_teenstudy/data/dxx_push_list.json
nonebot_plugin_auto_teenstudy/data/dxx_zj.json
nonebot_plugin_auto_teenstudy/dxx.py
nonebot_plugin_auto_teenstudy/getData.py
nonebot_plugin_auto_teenstudy/handle_dxx_data.py
nonebot_plugin_auto_teenstudy/msg_pic.py
nonebot_plugin_auto_teenstudy/resource/area/上海地区.md
nonebot_plugin_auto_teenstudy/resource/area/吉林地区.md
nonebot_plugin_auto_teenstudy/resource/area/四川地区.md
nonebot_plugin_auto_teenstudy/resource/area/安徽地区.md
nonebot_plugin_auto_teenstudy/resource/area/山东地区.md
nonebot_plugin_auto_teenstudy/resource/area/江西地区.md
nonebot_plugin_auto_teenstudy/resource/area/浙江地区.md
nonebot_plugin_auto_teenstudy/resource/area/湖北地区.md
nonebot_plugin_auto_teenstudy/resource/area/重庆地区.md
nonebot_plugin_auto_teenstudy/resource/crawl/crawjx.py
nonebot_plugin_auto_teenstudy/resource/crawl/crawlsc.py
nonebot_plugin_auto_teenstudy/resource/crawl/crawlzj.py
nonebot_plugin_auto_teenstudy/resource/dxx_bg/answer_bg.png
nonebot_plugin_auto_teenstudy/resource/dxx_bg/dxx_1.jpg
nonebot_plugin_auto_teenstudy/resource/dxx_bg/dxx_2.jpg
nonebot_plugin_auto_teenstudy/resource/dxx_bg/dxx_3.jpg
nonebot_plugin_auto_teenstudy/resource/dxx_bg/dxx_4.jpg
nonebot_plugin_auto_teenstudy/resource/dxx_bg/dxx_5.jpg
nonebot_plugin_auto_teenstudy/resource/endpic/2022年特辑.jpg
nonebot_plugin_auto_teenstudy/resource/endpic/2022年第10期.jpg
nonebot_plugin_auto_teenstudy/resource/endpic/2022年第11期.jpg
nonebot_plugin_auto_teenstudy/resource/endpic/2022年第12期.jpg
nonebot_plugin_auto_teenstudy/resource/endpic/2022年第13期.jpg
nonebot_plugin_auto_teenstudy/resource/endpic/2022年第14期.jpg
nonebot_plugin_auto_teenstudy/resource/endpic/2022年第15期.jpg
nonebot_plugin_auto_teenstudy/resource/endpic/2022年第16期.jpg
nonebot_plugin_auto_teenstudy-0.1.9.dist-info/LICENSE
nonebot_plugin_auto_teenstudy-0.1.9.dist-info/METADATA
nonebot_plugin_auto_teenstudy-0.1.9.dist-info/WHEEL
nonebot_plugin_auto_teenstudy-0.1.9.dist-info/RECORD
