Metadata-Version: 2.1
Name: nonebot-plugin-auto-teenstudy
Version: 0.1.9
Summary: 基于nonebot异步框架的青年大学自动提交插件
Home-page: https://github.com/ZM25XC/nonebot_plugin_auto_teenstudy
License: MIT
Author: ZM25XC
Author-email: xingling25@qq.com
Requires-Python: >=3.8,<4.0
Classifier: License :: OSI Approved :: MIT License
Classifier: Programming Language :: Python :: 3
Classifier: Programming Language :: Python :: 3.8
Classifier: Programming Language :: Python :: 3.9
Classifier: Programming Language :: Python :: 3.10
Classifier: Programming Language :: Python :: 3.11
Requires-Dist: Pillow (>=9.4.0,<10.0.0)
Requires-Dist: anti-useragent (>=1.0.10,<2.0.0)
Requires-Dist: beautifulsoup4 (>=4.11.2,<5.0.0)
Requires-Dist: bs4 (>=0.0.1,<0.0.2)
Requires-Dist: fastapi (>=0.95.0,<0.96.0)
Requires-Dist: httpx (>=0.24.0,<0.25.0)
Requires-Dist: lxml (>=4.9.2,<5.0.0)
Requires-Dist: nonebot-adapter-onebot (>=2.2.3,<3.0.0)
Requires-Dist: nonebot-plugin-apscheduler (>=0.3.0,<0.4.0)
Requires-Dist: nonebot2 (>=2.0.0,<3.0.0)
